CONTRIBUTING.md
MANIFEST.in
README.rst
setup.py
docs/HISTORY.txt
docs/LICENSE.GPL
docs/LICENSE.txt
eea/__init__.py
eea.banner.egg-info/PKG-INFO
eea.banner.egg-info/SOURCES.txt
eea.banner.egg-info/dependency_links.txt
eea.banner.egg-info/entry_points.txt
eea.banner.egg-info/namespace_packages.txt
eea.banner.egg-info/not-zip-safe
eea.banner.egg-info/requires.txt
eea.banner.egg-info/top_level.txt
eea/banner/README.txt
eea/banner/__init__.py
eea/banner/configure.zcml
eea/banner/interfaces.py
eea/banner/profiles.zcml
eea/banner/setuphandlers.py
eea/banner/version.txt
eea/banner/browser/__init__.py
eea/banner/browser/configure.zcml
eea/banner/browser/controlpanel.py
eea/banner/locales/__init__.py
eea/banner/locales/eea.pot
eea/banner/locales/plone-manual.pot
eea/banner/locales/update.sh
eea/banner/locales/bg/LC_MESSAGES/eea.po
eea/banner/locales/bg/LC_MESSAGES/plone.po
eea/banner/locales/cs/LC_MESSAGES/eea.po
eea/banner/locales/cs/LC_MESSAGES/plone.po
eea/banner/locales/da/LC_MESSAGES/eea.po
eea/banner/locales/da/LC_MESSAGES/plone.po
eea/banner/locales/de/LC_MESSAGES/eea.po
eea/banner/locales/de/LC_MESSAGES/plone.po
eea/banner/locales/el/LC_MESSAGES/eea.po
eea/banner/locales/el/LC_MESSAGES/plone.po
eea/banner/locales/en/LC_MESSAGES/eea.po
eea/banner/locales/en/LC_MESSAGES/plone.po
eea/banner/locales/es/LC_MESSAGES/eea.po
eea/banner/locales/es/LC_MESSAGES/plone.po
eea/banner/locales/et/LC_MESSAGES/eea.po
eea/banner/locales/et/LC_MESSAGES/plone.po
eea/banner/locales/eu/LC_MESSAGES/eea.po
eea/banner/locales/eu/LC_MESSAGES/plone.po
eea/banner/locales/fi/LC_MESSAGES/eea.po
eea/banner/locales/fi/LC_MESSAGES/plone.po
eea/banner/locales/fr/LC_MESSAGES/eea.po
eea/banner/locales/fr/LC_MESSAGES/plone.po
eea/banner/locales/hr/LC_MESSAGES/eea.po
eea/banner/locales/hr/LC_MESSAGES/plone.po
eea/banner/locales/hu/LC_MESSAGES/eea.po
eea/banner/locales/hu/LC_MESSAGES/plone.po
eea/banner/locales/is/LC_MESSAGES/eea.po
eea/banner/locales/is/LC_MESSAGES/plone.po
eea/banner/locales/it/LC_MESSAGES/eea.po
eea/banner/locales/it/LC_MESSAGES/plone.po
eea/banner/locales/kl/LC_MESSAGES/eea.po
eea/banner/locales/kl/LC_MESSAGES/plone.po
eea/banner/locales/lt/LC_MESSAGES/eea.po
eea/banner/locales/lt/LC_MESSAGES/plone.po
eea/banner/locales/lv/LC_MESSAGES/eea.po
